MultiExtractiveSummarizer/__init__.py
MultiExtractiveSummarizer/embeddings.py
MultiExtractiveSummarizer/multi_extractive_summarizer.py
MultiExtractiveSummarizer/methods/__init__.py
MultiExtractiveSummarizer/methods/kmeans.py
MultiExtractiveSummarizer/methods/kmeans2.py
MultiExtractiveSummarizer/methods/lexrank.py
MultiExtractiveSummarizer/methods/textrank.py
MultiExtractiveSummarizer-0.2.3.dist-info/LICENSE
MultiExtractiveSummarizer-0.2.3.dist-info/METADATA
MultiExtractiveSummarizer-0.2.3.dist-info/WHEEL
MultiExtractiveSummarizer-0.2.3.dist-info/top_level.txt
MultiExtractiveSummarizer-0.2.3.dist-info/RECORD
