Metadata-Version: 2.1
Name: MultiExtractiveSummarizer
Version: 0.2.3
Summary: Python package for extractive text summarization using various embeddings and methods.
Home-page: https://github.com/arshraj-r/MultiExtractiveSummarizer.git
Author: Arshraj Randhawa
Author-email: arshraj.randhawa@gmail.com
Classifier: Programming Language :: Python :: 3
Classifier: License :: OSI Approved :: MIT License
Classifier: Operating System :: OS Independent
Requires-Python: >=3.6
License-File: LICENSE
Requires-Dist: nltk
Requires-Dist: sentence-transformers
Requires-Dist: scipy
Requires-Dist: scikit-learn
